{"components_arrow.md":"hIQx528x","components_itemlist.md":"zBAnG7KL","components_licenseinfo.md":"0GO_Q5wq","components_itemsuggest.md":"DP60z7a4","components_autolink.md":"rb3ixW3_","utilities_cdkregistrytosuggestfunction.md":"DT8vPuU9","components_modal.md":"CO4v07qx","index.md":"KBlh4TBW","utilities_draganddrop.md":"CFH7Fe79","components_itemdetails.md":"C14T_9nl","utilities_datetostring.md":"BZpMOV-b","utilities_debounce.md":"BtK3vvI5","components_concepttree.md":"Cqj0uYrl","components_loadingindicator.md":"B5ra5SL_","utilities_addclickhandlers.md":"CzrIU8PE","components_itemname.md":"DTsymsoF"}
